ceylon_rag/__init__.py
ceylon_rag/factory/__init__.py
ceylon_rag/factory/component_factory.py
ceylon_rag/impl/__init__.py
ceylon_rag/impl/embedders/__init__.py
ceylon_rag/impl/embedders/ollama_embedder.py
ceylon_rag/impl/embedders/openai_embedder.py
ceylon_rag/impl/llms/__init__.py
ceylon_rag/impl/llms/ollama.py
ceylon_rag/impl/llms/openai.py
ceylon_rag/impl/loaders/__init__.py
ceylon_rag/impl/loaders/image_loader.py
ceylon_rag/impl/loaders/pdf_loader.py
ceylon_rag/impl/loaders/text_loader.py
ceylon_rag/impl/loaders/universal_text_loader.py
ceylon_rag/impl/vector_stores/__init__.py
ceylon_rag/impl/vector_stores/lancedb_store.py
ceylon_rag/interfaces/__init__.py
ceylon_rag/interfaces/base.py
ceylon_rag/interfaces/document_loader.py
ceylon_rag/interfaces/embedder.py
ceylon_rag/interfaces/llm.py
ceylon_rag/interfaces/schemas.py
ceylon_rag/interfaces/vector_store.py
ceylon_rag-0.3.1.dist-info/METADATA
ceylon_rag-0.3.1.dist-info/WHEEL
ceylon_rag-0.3.1.dist-info/RECORD
