Metadata-Version: 2.1
Name: ceylon-rag
Version: 0.3.1
Summary: 
Author: dewma
Author-email: dewmal@syigen.com
Requires-Python: >=3.12,<4.0
Classifier: Programming Language :: Python :: 3
Classifier: Programming Language :: Python :: 3.12
Classifier: Programming Language :: Python :: 3.13
Requires-Dist: aiohttp (>=3.11.11,<4.0.0)
Requires-Dist: aioresponses (>=0.7.7,<0.8.0)
Requires-Dist: asyncio (>=3.4.3,<4.0.0)
Requires-Dist: lancedb (==0.18.0)
Requires-Dist: numpy (>=2.2.1,<3.0.0)
Requires-Dist: ollama (>=0.4.6,<0.5.0)
Requires-Dist: openai (>=1.59.6,<2.0.0)
Requires-Dist: pandas (>=2.2.3,<3.0.0)
Requires-Dist: pillow (>=11.1.0,<12.0.0)
Requires-Dist: pydantic (>=2.10.5,<3.0.0)
Requires-Dist: pypdf (>=5.1.0,<6.0.0)
Requires-Dist: pytesseract (>=0.3.13,<0.4.0)
Requires-Dist: pytest (>=8.3.4,<9.0.0)
Requires-Dist: pytest-asyncio (>=0.25.2,<0.26.0)
Requires-Dist: python-dotenv (>=1.0.1,<2.0.0)
Requires-Dist: python-magic (>=0.4.27,<0.5.0)
Requires-Dist: reportlab (>=4.2.5,<5.0.0)
Requires-Dist: tantivy (>=0.22.0,<0.23.0)
Requires-Dist: tenacity (>=9.0.0,<10.0.0)
